<?xml version="1.0" encoding="utf-8"?>
<Language>
  <Section name="system">
    <String name="0" text="Avslutt"/>
    <String name="1" text="Ugyldig streng"/>
    <String name="2" text="tim"/>
    <String name="3" text="min"/>
    <String name="4" text="sek"/>
    <String name="5" text="Meny"/>
    <String name="eject" text="Løs ut"/>
    <String name="yes" text="ja"/>
    <String name="no" text="nei"/>
  </Section>
  <Section name="general">
    <String name="name" text="Navn"/>
    <String name="date" text="Dato"/>
    <String name="size" text="Størrelse"/>
    <String name="view" text="Vis"/>
    <String name="sort" text="Sorter"/>
    <String name="options" text="Instillinger"/>
    <String name="tags" text="Tagger"/>
    <String name="filename" text="Filnavn"/>
  </Section>
  <Section name="days">
    <String name="0" text="Søndag"/>
    <String name="1" text="Mandag"/>
    <String name="2" text="Tirsdag"/>
    <String name="3" text="Onsdag"/>
    <String name="4" text="Torsdag"/>
    <String name="5" text="Fredag"/>
    <String name="6" text="Lørdag"/>
  </Section>
  <Section name="importers">
    <String name="addshare" text="Legg til delt"/>
    <String name="removeshare" text="Fjern delt"/>
    <String name="refresh" text="Oppdater database"/>
  </Section>
  <Section name="shares">
    <String name="shares" text="Oppsett av Bibliotek"/>
    <String name="addnewshares" text="Legg til mapper for overvåking"/>
    <String name="removeshares" text="Fjern overvåkning av mapper"/>
    <String name="done" text="Ferdig"/>
    <String name="description" text="Legg til eller fjern mapper fra Biblioteket"/>
    <String name="selectsharetoremove" text="Velg mapper du ikke vill overvåke lenger"/>
    <String name="selectsharestoadd" text="Velg mapper som du vil legge til i biblioteket"/>
    <String name="back" text="Tilbake"/>
    <String name="cancel" text="Avbryt"/>
  </Section>
  <Section name="playback">
    <String name="0" text="Zoom modus"/>
    <String name="1" text="Forrige vindu"/>
    <String name="2" text="Beskjæring"/>
    <String name="3" text="Språk for undertekst"/>
    <String name="4" text="Lydspråk"/>
    <String name="5" text="start"/>
    <String name="6" text="slutt"/>
    <String name="7" text="Letterbox 4:3"/>
    <String name="8" text="Normal"/>
    <String name="9" text="Original"/>
    <String name="10" text="Pan&amp;Scan"/>
    <String name="11" text="Strekt"/>
    <String name="12" text="Zoom"/>
    <String name="13" text="Zoom 14:9"/>
    <String name="14" text="Undertekster"/>
    <String name="15" text="Venstre topp"/>
    <String name="16" text="Høyre bunn"/>
    <String name="17" text="Av"/>
    <String name="18" text=" (voksen)"/>
    <String name="19" text=" (barn)"/>
    <String name="20" text=" (CC)"/>
    <String name="21" text=" (CC voksen)"/>
    <String name="22" text=" (CC barn)"/>
    <String name="23" text=" (tvungen)"/>
    <String name="24" text=" (Regissørens kommentar)"/>
    <String name="25" text=" (Regissørens kommentar voksen)"/>
    <String name="26" text=" (Regissørens kommentar 2)"/>
    <String name="27" text=" (Visually Impaired)"/>
    <String name="28" text="Titler"/>
    <String name="29" text="Kapittel"/>
    <String name="30" text="PiP"/>
    <String name="31" text="Slå av"/>
    <String name="32" text="Bytte"/>
    <String name="33" text="Stoppet"/>
    <String name="34" text="Ferdig"/>
    <String name="35" text="Fortsett"/>
    <String name="36" text="Start på nytt"/>
    <String name="37" text="Slette"/>
    <String name="38" text="Slutt"/>
    <String name="intelligentzoom" text="Intelligent Zoom"/>
  </Section>
  <Section name="movies">
    <String name="0" text="Navn"/>
    <String name="1" text="Dato"/>
    <String name="2" text="Størrelse"/>
    <String name="duration" text="Lengde"/>
    <String name="3" text="Mine Filmer"/>
    <String name="4" text="Vis"/>
    <String name="5" text="Sorter"/>
    <String name="6" text="Spill DVD"/>
    <String name="7" text="Løs ut"/>
    <String name="8" text="Visning"/>
    <String name="dvd" text="DVD Bibliotek"/>
  </Section>
  <Section name="music">
    <String name="0" text="Navn"/>
    <String name="1" text="Dato"/>
    <String name="2" text="Størrelse"/>
    <String name="3" text="Min Musikk"/>
    <String name="4" text="Vis"/>
    <String name="5" text="Sorter"/>
    <String name="6" text="Spill CD"/>
    <String name="7" text="Løs ut"/>
    <String name="8" text="Velg visning"/>
    <String name="settings" text="Instillinger"/>
    <String name="settingsgeneral" text="Generelt"/>
    <String name="settingsfade" text="Fade ved stopp"/>
    <String name="settingsgapless" text="Gapless avspilling"/>
  </Section>
  <Section name="media">
    <String name="name" text="Min Media"/>
  </Section>
  <Section name="home">
    <String name="title" text="MediaPortal"/>
  </Section>
  <Section name="login">
    <String name="welcome" text="velkommen"/>
  </Section>
  <Section name="weather">
    <String name="0" text="Mitt Vær"/>
    <String name="1" text="Sted"/>
    <String name="2" text="Oppfrisk"/>
    <String name="3" text="Vær"/>
    <String name="4" text="Instillinger"/>
    <String name="5" text="ingen data"/>
    <String name="6" text="Temp"/>
    <String name="7" text="Føles som"/>
    <String name="8" text="UV Indeks"/>
    <String name="9" text="Vind"/>
    <String name="10" text="Fuktighet"/>
    <String name="11" text="Doggpunkt"/>
    <String name="12" text="Soloppgang"/>
    <String name="13" text="Solnedgang"/>
    <String name="370" text="T-Storm"/>
    <String name="371" text="Delvis"/>
    <String name="372" text="Mesteparten"/>
    <String name="373" text="Sol"/>
    <String name="374" text="Overskyet"/>
    <String name="375" text="Snø"/>
    <String name="376" text="Regn"/>
    <String name="377" text="Lyst"/>
    <String name="378" text="AM"/>
    <String name="379" text="PM"/>
    <String name="380" text="Skyet"/>
    <String name="381" text="Noen få"/>
    <String name="382" text="Spredt"/>
    <String name="383" text="Vind"/>
    <String name="384" text="Sterk"/>
    <String name="386" text="Klart"/>
    <String name="387" text="Tidlig"/>
    <String name="389" text="Tåke"/>
    <String name="390" text="Disig"/>
    <String name="391" text="Vindfull"/>
    <String name="392" text="Duskregn"/>
    <String name="393" text="Frysing"/>
    <String name="394" text="N/A"/>
    <String name="395" text="Yr"/>
    <String name="798" text="lav"/>
    <String name="799" text="høy"/>
    <String name="543" text="Torden"/>
    <String name="553" text="Sen"/>
    <String name="535" text="N"/>
    <String name="536" text="Ø"/>
    <String name="537" text="S"/>
    <String name="538" text="V"/>
    <String name="539" text="NØ"/>
    <String name="540" text="SØ"/>
    <String name="541" text="SV"/>
    <String name="542" text="NV"/>
    <String name="543" text="Torden"/>
    <String name="544" text="NNØ"/>
    <String name="545" text="ØNØ"/>
    <String name="546" text="ØSØ"/>
    <String name="547" text="SSØ"/>
    <String name="548" text="SSV"/>
    <String name="549" text="VSV"/>
    <String name="551" text="VNV"/>
    <String name="552" text="NNV"/>
    <String name="555" text="Fra {0} med {1} {2}"/>
    <String name="556" text="variert"/>
    <String name="557" text="rolig"/>
    <String name="558" text="Ingen vind"/>
    <String name="559" text="i nærheten"/>
    <String name="560" text="Klarner"/>
  </Section>
  <Section name="weathersetup">
    <String name="0" text="Vennligst skriv inn navnet på din by!"/>
    <String name="1" text="Søk"/>
    <String name="2" text="Velg..."/>
    <String name="3" text="Lagre"/>
  </Section>
  <Section name="pictures">
    <String name="0" text="Tittel"/>
    <String name="1" text="Tagger"/>
    <String name="2" text="Størrelse"/>
    <String name="3" text="Mine Bilder"/>
    <String name="4" text="Velg visning"/>
    <String name="5" text="Sorter"/>
    <String name="6" text="Lysbilde"/>
    <String name="picinfo" text="Bilde informasjon"/>
    <String name="save" text="Lagre"/>
    <String name="cancel" text="Avbryt"/>
    <String name="crop" text="Beskjær"/>
    <String name="print" text="Skriv ut"/>
    <String name="redeye" text="Fjern røde øyne"/>
    <String name="contrast" text="Kontrast"/>
    <String name="edit" text="Endre"/>
    <String name="model" text="Kameramodell"/>
    <String name="maker" text="Forfatter"/>
    <String name="flash" text="Blitz"/>
    <String name="dimension" text="Dimensjoner"/>
    <String name="expcomp" text="Eksponeringsavvik"/>
    <String name="exptime" text="Eksponeringstid"/>
    <String name="metmod" text="Målingsmodus"/>
    <String name="sspeed" text="Lukker hastighet"/>
    <String name="fstop" text="F Stopp"/>
  </Section>
  <Section name="settings">
    <String name="0" text="Instillinger"/>
    <String name="1" text="Skinn"/>
    <String name="2" text="Språk"/>
    <String name="3" text="Lagre"/>
    <String name="4" text="Fullskjerm"/>
    <String name="theme" text="Tema"/>
    <String name="mpg2videocodec" text="MPEG-2 Video Codec"/>
    <String name="h264videocodec" text="H-264 Video Codec"/>
    <String name="xvidvideocodec" text="DivX/XVID Video Codec"/>
    <String name="audiocodec" text="Lyd Codec"/>
    <String name="playback" text="Avspilling"/>
    <String name="refreshrate" text="Refresh rate"/>
    <String name="5" text="Instilling for Refresh Rate"/>
    <String name="6" text="24 FPS"/>
    <String name="7" text="25 FPS"/>
    <String name="8" text="30 FPS"/>
    <String name="9" text="Standard FPS"/>
    <String name="music" text="Musikk"/>
    <String name="appearance" text="Utseende"/>
    <String name="audiosetup" text="Lyd oppsett"/>
    <String name="speakersetup" text="Velg hvordan høytalerene er tilkoblet"/>
    <String name="buildin" text="Innebygd (laptop)"/>
    <String name="analog" text="Analog"/>
    <String name="digital" text="Digital (Toslink/coax)"/>
    <String name="speakeramount" text="Velg antall høytalere"/>
    <String name="speakers2" text="2 høytalere (stereo)"/>
    <String name="speakers51" text="5.1 høytalere"/>
    <String name="speakers71" text="7.1 høytalere"/>
    <String name="tvsetup" text="Tv/Monitor oppsett"/>
    <String name="monitorsetup" text="Velg TV/monitor type"/>
    <String name="monitorcrt" text="CRT"/>
    <String name="monitorlcd" text="LCD/Plasma"/>
    <String name="monitorprojector" text="Projektor"/>
    <String name="monitorarsetup" text="Velg din tv/monitor"/>
    <String name="monitornormal" text="Normal (4:3)"/>
    <String name="monitorwide" text="Wide (16:9)"/>
    <String name="monitorbuildin" text="Innebygd"/>
    <String name="next" text="Neste"/>
    <String name="back" text="Tilbake"/>
    <String name="finish" text="Ferdig"/>
  </Section>
  <Section name="radio">
    <String name="name" text="Min Radio"/>
  </Section>
  <Section name="tv">
    <String name="name" text="Min Tv"/>
  </Section>
  <Section name="playlists">
    <String name="add" text="Legg til i spilleliste"/>
    <String name="addall" text="Legg alle til i spillelisten"/>
    <String name="playlist" text="Spilleliste"/>
    <String name="play" text="Spill av"/>
    <String name="clear" text="Slett"/>
    <String name="shuffle" text="Blande"/>
    <String name="load" text="Hent"/>
  </Section>
  <Section name="extensions">
    <String name="myextensions" text="Mine Tilegg"/>
    <String name="updateall" text="Oppdater alle"/>
    <String name="settings" text="Innstillinger"/>
    <String name="view" text="Vis"/>
    <String name="sort" text="Sorter"/>
    <String name="views" text="Velg visning"/>
    <String name="install" text="Installere"/>
    <String name="uninstall" text="Avinstallere"/>
    <String name="downloadinstall" text="Last ned og installer"/>
    <String name="downloadlist" text="Oppdater liste"/>
    <String name="cancelinstall" text="Avbryt installasjonen"/>
    <String name="canceluninstall" text="Avbryt avinstalleringen"/>
    <String name="cancelreinstall" text="Avbryt installasjon på nytt"/>
    <String name="cancelupdate" text="Avbryt oppdatering"/>
    <String name="name" text="Navn"/>
    <String name="downloads" text="Nedlastninger"/>
    <String name="size" text="Størrelse"/>
    <String name="date" text="Dato"/>
    <String name="reinstall" text="Installer på nytt"/>
    <String name="installinfo" text="Denne kommandoen vil bli utført neste gang MediaPortal startes"/>
    <String name="dependecyinfo" text="Dette tilegget krever en eller flere andre tilegg som også vil bli installert. Fortsette ?"/>
    <String name="notification" text="Beskjed"/>
    <String name="dependon" text="Er avhengig av"/>
    <String name="flatview" text="Flat"/>
    <String name="collection" text="Kolleksjon"/>
    <String name="update" text="Oppdater"/>
  </Section>
  <Section name="list">
    <String name="small" text="Liten Liste"/>
    <String name="big" text="Stor Liste"/>
    <String name="thumbs" text="Ikoner"/>
    <String name="coverthrow" text="Coverthrow"/>
    <String name="coverflow" text="Coverflow"/>
  </Section>
</Language>