<?xml version='1.0' encoding='UTF-8'?>
<resources>
  <string name="Settings.Players">Spilari</string>
  <string name="Settings.Players.Rendering">Þýða</string>
  <string name="Settings.Players.Rendering.CrossFading">Skarast</string>
  <string name="Settings.Players.Rendering.CrossFading.CrossFadingEnabled">Að leyfa skörun</string>
  <string name="Settings.Players.Rendering.CrossFading.CrossFadingEnabled.Help">Ákvarða hvort að Mediaportal eigi að láta lög skarast ef það er mögulegt</string>
  <string name="Settings.Players.Rendering.CrossFading.CrossFadeDuration">Tímalengd skörunar</string>
  <string name="Settings.Players.Rendering.CrossFading.CrossFadeDuration.Help">Skörun í sekúndum</string>
</resources>
