<?xml version='1.0' encoding='UTF-8'?>
<resources>
  <string name="System.Yes">Jah</string>
  <string name="System.No">Ei</string>
  <string name="System.Done">Valmis</string>
  <string name="System.Finish">Lõpeta</string>
  <string name="System.Ok">OK</string>
  <string name="System.Cancel">Loobu</string>
  <string name="System.Discard">Heida minema</string>
  <string name="System.Back">Tagasi</string>
  <string name="System.Continue">Jätka</string>
  <string name="System.Add">Lisa</string>
  <string name="System.Remove">Eemalda</string>
  <string name="System.Hint">Vihje</string>
  <string name="System.Information">Info</string>
  <string name="System.Warning">Hoiatus</string>
  <string name="System.Error">viga</string>
  <string name="Keys.Shift">Nihuta</string>
  <string name="Keys.CapsLock">Caps Lock</string>
  <string name="Keys.AltGr">Alt Gr</string>
  <string name="Home.Title">MediaPortal 2</string>
  <string name="Home.HomeStateDisplayLabel">Algvaade</string>
  <string name="Dialogs.InfoHeaderText">Info</string>
  <string name="Dialogs.WarningHeaderText">Hoiatus</string>
  <string name="Dialogs.ErrorHeaderText">Viga</string>
  <string name="Media.MyMusic">Muusika</string>
  <string name="Media.MyVideos">Videod</string>
  <string name="Media.MyPictures">Pildid</string>
  <string name="ServerConnection.NotificationServerAvailableTitle">MP2 server saadaval</string>
  <string name="ServerConnection.NotificationServerAvailableText">Vähemalt üks MP2 server saadaval, ühenda see MediaPortal 2 kõigi võimaluste kasutamiseks.</string>
  <string name="ServerConnection.ServerFormatText">\'{0}\' hostil \'{1}\'</string>
  <!--{0} = server name, {1} = host name-->
  <string name="ServerConnection.UnknownServerName">&lt;Unknown&gt;</string>
  <string name="ServerConnection.UnknownServerSystem">&lt;Unknown&gt;</string>
  <string name="ServerConnection.HomeServer">Koduserver</string>
  <string name="ServerConnection.AttachToServerWorkflowStateLabel">Ühenda serveriga</string>
  <string name="ServerConnection.DetachFromServerWorkflowStateLabel">Eraldu serverist</string>
  <string name="ServerConnection.HomeServerWorkflowStateLabel">Koduserver</string>
  <string name="ServerConnection.AttachedText.Before">See MP2 kasutaja on hetkel ühendatud koduserveriga</string>
  <string name="ServerConnection.AttachedText.After"></string>
  <string name="ServerConnection.NoHomeServerAttached">See MP2 kasutaja ei ole hetkel ühendatud koduserveriga</string>
  <string name="ServerConnection.HomeServerIsConnected">Koduserver on hetkel ühendatud</string>
  <string name="ServerConnection.HomeServerIsNotConnected">Koduserver on hetkel eraldatud</string>
  <string name="ServerConnection.DetachMenu">Eralda</string>
  <string name="ServerConnection.DetachConfirmDialogHeader">Eraldu koduserverist</string>
  <string name="ServerConnection.SearchForServers">Serveri otsimine</string>
  <string name="ServerConnection.DetachFromServer">Eraldu koduserverist</string>
  <string name="ServerConnection.AttachToServerHeader">Ühendu MediaPortal 2 serveriga</string>
  <string name="ServerConnection.AttachToMultipleText">Võrgus on mitu MP 2 serverit. Kas soovid neist ühe koduserveriks valida?</string>
  <string name="ServerConnection.AttachToSingleText.Before">MP 2 server</string>
  <string name="ServerConnection.AttachToSingleText.After">on võrgus saadaval. Kas ühendada?</string>
  <string name="ServerConnection.AttachToServerNoServerText">Võrgus ei ole MediaPortal 2 serverit saadaval.</string>
  <string name="ServerConnection.AttachButton">Lisa</string>
  <string name="ServerConnection.AttachInfoDialogHeader">Server ühendatud</string>
  <string name="ServerConnection.AttachInfoDialogText">MediaPortal 2 klient on ühendatud uue koduserveriga \'{0}\' hostil \'{1}\'</string>
  <!--{0} = server name, {1} = host name-->
  <string name="Notifications.Title">Teatised</string>
  <string name="Notifications.OneMoreNotification">(1 veel)</string>
  <string name="Notifications.NMoreNotifications">({0} veel)</string>
  <string name="Notifications.WatchNotificationsWorkflowStateLabel">Teatised</string>
  <string name="Notifications.Handle">Käsitle</string>
  <string name="ImporterMessages.ImportStartedTitle">Import alustatud</string>
  <string name="ImporterMessages.ImportStartedText">\'{0}\' import  on alustatud</string>
  <string name="ImporterMessages.ImportCompletedTitle">Import valmis</string>
  <string name="ImporterMessages.ImportCompletedText">\'{0}\' import on valmis</string>
  <string name="LocalFsResourceProvider.Description">Pääs kohalikku failisüsteemi</string>
  <string name="RemoteResourceProvider.Description">Pääs teise MediaPortal 2 süsteemi ressurssi</string>
  <string name="ScreenSaver.MediaPortal2">MediaPortal 2</string>
  <!--For MP UI player subsystem-->
  <string name="Players.NoPlayerAvailableNotificationTitle">Pole pleierit</string>
  <string name="Players.NoPlayerAvailableNotificationText">Pole registreeritud pleierit \'{0}\' esitamiseks</string>
  <string name="Players.ErrorPlayingMediaItemTitle">Meedia esitamise viga</string>
  <string name="Players.UnableToPlayMediaItemText">Ei suuda esitada \'{0}\'</string>
  <string name="Players.ResourceNotFoundText">Ressussi \'{0}\' ei leia</string>
  <string name="Players.PlayerConfiguration">Pleieri seadistamine</string>
  <string name="Players.CurrentMediaInfo">Käesoleva meedia info</string>
  <string name="Players.FullscreenVideo">Täiskuva {0}</string>
  <!--for example "Fullscreen TV"-->
  <string name="Players.FullscreenImage">Täiskuva pilt</string>
  <string name="Players.AudioVisualization">Heli pilt</string>
  <string name="Players.PlayerOfType">{0} pleier</string>
  <!--for example "Video player"-->
  <string name="Players.SlotNo">Slot #{0}</string>
  <string name="Players.FocusPlayer">Foookus {0}</string>
  <!--for example "Focus video player"-->
  <string name="Players.SwitchPipPlayers">Vaheta PiP pleiereid</string>
  <string name="Players.ChooseAudioStream">Vali heliriba</string>
  <!--for example "Audio menu for Lammbock"-->
  <string name="Players.Mute">Mute</string>
  <string name="Players.MuteOff">Mute off</string>
  <string name="Players.ClosePlayerContext">Sulge {0}</string>
  <!--for example "Close video player"-->
  <string name="Players.ChoosePlayerGeometry">Zuum mode</string>
  <string name="Players.ChoosePlayerEffect">Effekt</string>
  <string name="Settings.Appearance">Väljanägemine</string>
  <string name="Settings.Appearance.Skin">Skin</string>
  <string name="Settings.Appearance.Skin.Formats.DateFormat">kuupäeva kuju</string>
  <string name="Settings.Appearance.Skin.Formats.DateFormat.Help">Skini kuupäeva kuju. Kasutage .net kuupäeva klassi seadeid</string>
  <string name="Settings.Appearance.Skin.Formats.TimeFormat">Aja kuju</string>
  <string name="Settings.Appearance.Skin.Formats.TimeFormat.Help">Skini aja kuju. Kasutage .net kuupäeva klassi seadeid</string>
  <string name="Settings.General">Üldine</string>
  <string name="Settings.General.System">Süsteem</string>
  <string name="Settings.General.System.Autostart">Autostart</string>
  <string name="Settings.General.System.Autostart.Help">Käivita Media Portal koos Windowsiga</string>
  <string name="Settings.General.Connectivity">Ühtesobivus</string>
  <string name="Settings.General.Connectivity.HomeServer">Koduserver</string>
  <string name="Settings.General.Connectivity.HomeServer.Help">Koduserveri info, koduserveriga ühendumine ja eraldumine.</string>
  <string name="Settings.General.Connectivity.ServerListener">Serverikuulaja</string>
  <string name="Settings.General.Connectivity.ServerListener.Help">Aktiveeri teatis kui MP 2 server tuleb võrgus sadavale.</string>
  <string name="Settings.General.Connectivity.ClientName">Kliendi nimi</string>
  <string name="Settings.General.Connectivity.ClientName.Help">Sea MP2 kliendi nimi</string>
  <string name="Settings.Regional">Piirkondlik</string>
  <string name="Settings.Regional.Language">Keel</string>
  <string name="Settings.Regional.Language.Main">Keel</string>
  <string name="Settings.Regional.Language.Main.Help">Sea põhikeeleks</string>
  <!--Section name-->
  <!--Group name-->
  <!--Setting-->
  <string name="Settings.Shares.Overview">Ülevaade</string>
  <!--Group name-->
  <!--Setting-->
  <string name="Settings.Plugins">Lisad</string>
  <string name="Shares.InvalidPath">VIGANE TEE: \'{0}\'</string>
  <!--For example: INVALID PATH: 'C:\XXX\YYY'-->
  <string name="Shares.Online">Online</string>
  <string name="Shares.Offline">Offline</string>
  <string name="Shares.ReImport">Taasimport</string>
  <string name="Shares.Importing">Impordin...</string>
  <!--Shares configuration workflow-->
  <string name="SharesConfig.SharesEditChooseResourceProviderWorkflowNavigationContextDisplayLabel">Vali ressursipakkuja</string>
  <string name="SharesConfig.SharesEditEditPathWorkflowNavigationContextDisplayLabel">Muuda teed</string>
  <string name="SharesConfig.SharesEditChoosePathWorkflowNavigationContextDisplayLabel">Vali tee</string>
  <string name="SharesConfig.SharesEditEditNameWorkflowNavigationContextDisplayLabel">Muuda nime</string>
  <string name="SharesConfig.SharesEditChooseCategoriesWorkflowNavigationContextDisplayLabel">Vali kategooriad</string>
  <string name="SharesConfig.ShareNameInfo">Nimi</string>
  <string name="SharesConfig.ShareResourceProviderInfo">Põhiressursi pakkuja</string>
  <string name="SharesConfig.ShareSystem">Süsteem:</string>
  <string name="SharesConfig.SharePathInfo">Tee:</string>
  <string name="SharesConfig.ShareResourcePathInfo">Tehniline tee:</string>
  <string name="SharesConfig.ShareMediaCategoriesInfo">Meedia kategooriad</string>
  <string name="SharesConfig.ChooseSystem">Vali süsteem</string>
  <string name="SharesConfig.ResourceProviderPathIsNotValid">Muuda lubatud teed valitud ressursipakkujas. Võib muuta lihtsat teed mis on ressursipakkujale arusaadav. Võib muuta teed ka kujul  {[Baasressursipakkuja-ID]}://[Baasressursipakkuja-Tee]&gt;{[Seotud ressursipakkuja-ID]}://[Seotud ressursipakkuja-Tee]&gt;..</string>
  <string name="SharesConfig.MenuEditShares">Muuda</string>
  <!--Must fit for both multiseat and singleseat, that's why we don't write "server share"-->
  <!--Must fit for both multiseat and singleseat, that's why we don't write "server share"-->
  <string name="SharesConfig.UpdateShareRelocateItemsQueryText.Query">Kas soovite taasimportida või asukohta muuta?</string>
  <string name="SharesConfig.Relocate">Muuda asukohta</string>
  <string name="SharesConfig.ReImport">Taasimpordi</string>
  <string name="UPnPFrontendServer.DefaultFriendlyName">MediaPartal 2 klient</string>
  <string name="UPnPFrontendServer.Manufacturer">Team Mediaportal</string>
  <string name="UPnPFrontendServer.ManufacturerUrl">www.team-mediaportal.com</string>
  <string name="UPnPFrontendServer.ModelName">MediaPortal 2 klient</string>
  <string name="UPnPFrontendServer.ModelNumber">1</string>
  <!--<string name="UPnPFrontendServer.ModelUrl">...</string>-->
  <string name="DaysOfWeek.1">Esmaspäev</string>
  <string name="DaysOfWeek.2">Teisipäev</string>
  <string name="DaysOfWeek.3">Kolmapäev</string>
  <string name="DaysOfWeek.4">Neljapäev</string>
  <string name="DaysOfWeek.5">Reede</string>
  <string name="DaysOfWeek.6">Laupäev</string>
  <string name="DaysOfWeek.7">Pühapäev</string>
  <string name="DaysOfWeek.Monday">Esmaspäev</string>
  <string name="DaysOfWeek.Tuesday">Teisipäev</string>
  <string name="DaysOfWeek.Wednesday">Kolmapäev</string>
  <string name="DaysOfWeek.Thursday">Neljapäev</string>
  <string name="DaysOfWeek.Friday">Reede</string>
  <string name="DaysOfWeek.Saturday">Laupäev</string>
  <string name="DaysOfWeek.Sunday">Pühapäev</string>
  <string name="Months.1">Jaanuar</string>
  <string name="Months.2">Veebruar</string>
  <string name="Months.3">Märts</string>
  <string name="Months.4">Aprill</string>
  <string name="Months.5">Mai</string>
  <string name="Months.6">Juuni</string>
  <string name="Months.7">Juuli</string>
  <string name="Months.8">August</string>
  <string name="Months.9">September</string>
  <string name="Months.10">Oktoober</string>
  <string name="Months.11">November</string>
  <string name="Months.12">Detsember</string>
  <string name="Months.January">Jaanuar</string>
  <string name="Months.February">Veebruar</string>
  <string name="Months.March">Märts</string>
  <string name="Months.April">Aprill</string>
  <string name="Months.May">Mai</string>
  <string name="Months.June">Juuni</string>
  <string name="Months.July">Juuli</string>
  <string name="Months.August">August</string>
  <string name="Months.September">September</string>
  <string name="Months.October">Oktoober</string>
  <string name="Months.November">November</string>
  <string name="Months.December">Detsember</string>
</resources>
