<?xml version="1.0" encoding="utf-8"?>
<resources>
  <string name="System.Yes">Yes</string>
  <string name="System.No">No</string>
  <string name="System.Done">Done</string>
  <string name="System.Finish">Finish</string>
  <string name="System.Ok">Ok</string>
  <string name="System.Cancel">Cancel</string>
  <string name="System.Discard">Discard</string>
  <string name="System.Back">Back</string>
  <string name="System.Continue">Continue</string>
  <string name="System.Add">Add</string>
  <string name="System.Remove">Remove</string>

  <string name="System.Hint">Hint</string>
  <string name="System.Information">Information</string>
  <string name="System.Warning">Warning</string>
  <string name="System.Error">Error</string>

  <string name="Keys.Shift">Shift</string>
  <string name="Keys.CapsLock">Caps Lock</string>
  <string name="Keys.AltGr">Alt Gr</string>
  <string name="Keys.Copy">Copy</string>
  <string name="Keys.Paste">Paste</string>

  <string name="Home.Title">MediaPortal 2</string>
  <string name="Home.HomeStateDisplayLabel">Home</string>

  <string name="Dialogs.InfoHeaderText">Info</string>
  <string name="Dialogs.WarningHeaderText">Warning</string>
  <string name="Dialogs.ErrorHeaderText">Error</string>

  <string name="Media.MyMusic">Music</string>
  <string name="Media.MyVideos">Videos</string>
  <string name="Media.MyPictures">Pictures</string>
  <string name="Media.InvalidShareName">Invalid media source</string>

  <string name="ServerConnection.NotificationServerAvailableTitle">MP2 server available</string>
  <string name="ServerConnection.NotificationServerAvailableText">There is at least one MediaPortal 2 server available in the network. Attach to it to get all features of MediaPortal 2.</string>
  <string name="ServerConnection.ServerFormatText">\'{0}\' at host \'{1}\'</string> <!-- {0} = server name, {1} = host name -->
  <string name="ServerConnection.UnknownServerName">&lt;Unknown&gt;</string>
  <string name="ServerConnection.UnknownServerSystem">&lt;Unknown&gt;</string>
  <string name="ServerConnection.HomeServer">Home server</string>
  <string name="ServerConnection.AttachToServerWorkflowStateLabel">Attach to server</string>
  <string name="ServerConnection.DetachFromServerWorkflowStateLabel">Detach from server</string>
  <string name="ServerConnection.HomeServerWorkflowStateLabel">HomeServer</string>
  <string name="ServerConnection.AttachedText.Before">This MediaPortal 2 client is currently attached to home server</string>
  <string name="ServerConnection.AttachedText.After"></string>
  <string name="ServerConnection.NoHomeServerAttached">Currently, this MediaPortal 2 client is not attached to a home server.</string>
  <string name="ServerConnection.HomeServerIsConnected">The home server is currently connected.</string>
  <string name="ServerConnection.HomeServerIsNotConnected">The home server is currently disconnected.</string>
  <string name="ServerConnection.DetachMenu">Detach</string>
  <string name="ServerConnection.DetachConfirmDialogHeader">Detach from home server</string>
  <string name="ServerConnection.DetachConfirmDialogText">If you detach from the home server, all data about the Client media sources and their media items will be removed from the home server\'s media library. You can attach again later. Do you really want to detach from home server \'{0}\' at host \'{1}\'?</string>
  <string name="ServerConnection.SearchForServers">Search for servers</string>
  <string name="ServerConnection.DetachFromServer">Detach from home server</string>
  <string name="ServerConnection.AttachToServerHeader">Attach to MediaPortal 2 server</string>
  <string name="ServerConnection.AttachToMultipleText">There are multiple MP2 servers available in the network. Do you want to choose one of them as home server?</string>
  <string name="ServerConnection.AttachToSingleText.Before">The MP2 server</string>
  <string name="ServerConnection.AttachToSingleText.After">is available in the network. Do you want to attach to it?</string>
  <string name="ServerConnection.AttachToServerNoServerText">Currently, there is no MediaPortal 2 server available in the network.</string>
  <string name="ServerConnection.AttachButton">Attach</string>
  <string name="ServerConnection.AttachInfoDialogHeader">Server attached</string>
  <string name="ServerConnection.AttachInfoDialogText">This MediaPortal 2 client was attached to its new home server \'{0}\' at host \'{1}\'</string> <!-- {0} = server name, {1} = host name -->

  <string name="Notifications.Title">Notifications</string>
  <string name="Notifications.OneMoreNotification">(1 more)</string>
  <string name="Notifications.NMoreNotifications">({0} more)</string>
  <string name="Notifications.WatchNotificationsWorkflowStateLabel">Notifications</string>
  <string name="Notifications.Handle">Handle</string>

  <string name="ImporterMessages.ImportStartedTitle">Import started</string>
  <string name="ImporterMessages.ImportStartedText">The import of \'{0}\' has started.</string>
  <string name="ImporterMessages.ImportCompletedTitle">Import completed</string>
  <string name="ImporterMessages.ImportCompletedText">The import of \'{0}\' has finished.</string>

  <string name="LocalFsResourceProvider.Name">Local filesystem</string>
  <string name="LocalFsResourceProvider.Description">Access the local filesystem</string>

  <string name="RemoteResourceProvider.Name">Remote resources</string>
  <string name="RemoteResourceProvider.Description">Access resources located at another MediaPortal 2 system</string>

  <string name="RawUrlResourceProvider.Name">Raw Url</string>
  <string name="RawUrlResourceProvider.Description">Access raw Uri sources</string>

  <string name="VirtualResourceProvider.Name">Virtual resources</string>
  <string name="VirtualResourceProvider.Description">Access virtual resources</string>

  <string name="ScreenSaver.MediaPortal2">MediaPortal 2</string>

  <!-- For MP UI player subsystem -->
  <string name="Players.NoPlayerAvailableNotificationTitle">No player</string>
  <string name="Players.NoPlayerAvailableNotificationText">There is no player registered to play media item \'{0}\'</string>
  <string name="Players.ErrorPlayingMediaItemTitle">Error playing media item</string>
  <string name="Players.UnableToPlayMediaItemText">Unable to play media item \'{0}\'</string>
  <string name="Players.ResourceNotFoundText">Resource \'{0}\' not found</string>

  <string name="Players.PlayerConfiguration">Player configuration</string>
  <string name="Players.CurrentMediaInfo">Current media info</string>
  <string name="Players.FullscreenVideo">Fullscreen {0}</string> <!--for example "Fullscreen TV" -->
  <string name="Players.FullscreenImage">Fullscreen image</string>
  <string name="Players.AudioVisualization">Audio visualization</string>
  <string name="Players.PlayerOfType">{0} player</string> <!-- for example "Video player" -->
  <string name="Players.SlotNo">Slot #{0}</string>
  <string name="Players.FocusPlayer">Focus {0}</string> <!-- for example "Focus video player" -->
  <string name="Players.SwitchPipPlayers">Switch PiP players</string>
  <string name="Players.ChooseAudioStream">Choose audio stream</string>
  <string name="Players.PlayerSlotAudioMenu">Audio menu for {0}</string> <!-- for example "Audio menu for Lammbock" -->
  <string name="Players.Mute">Mute</string>
  <string name="Players.MuteOff">Mute off</string>
  <string name="Players.ClosePlayerContext">Close {0}</string> <!-- for example "Close video player" -->
  <string name="Players.ChoosePlayerGeometry">Zoom mode</string>
  <string name="Players.ChoosePlayerEffect">Effect</string>
  <string name="Players.ChoosePlayerSubtitle">Subtitle</string>

  <string name="Settings.Appearance">Appearance</string>
  <string name="Settings.Appearance.Skin">Skin</string>
  <string name="Settings.Appearance.Skin.Formats.DateFormat">Date format</string>
  <string name="Settings.Appearance.Skin.Formats.DateFormat.Help">Date format used in the skin. Use 'd' for "1/14/2017" or 'D' for "Saturday, 1/14/2017".</string>
  <string name="Settings.Appearance.Skin.Formats.TimeFormat">Time format</string>
  <string name="Settings.Appearance.Skin.Formats.TimeFormat.Help">Time format used in the skin. Use 't' for "11:50" or 'T' for "11:50:37".</string>

  <string name="Settings.General">General</string>
  <string name="Settings.General.System">System</string>
  <string name="Settings.General.System.Autostart">Autostart</string>
  <string name="Settings.General.System.Autostart.Help">Start MediaPortal automatically on Windows startup</string>

  <string name="Settings.General.System.ClientDOKANDrive">Resource mounting drive letter</string>
  <string name="Settings.General.System.ClientDOKANDrive.Help">Configures the drive letter for mounting remote resources on this client.</string>

  <string name="Settings.General.Connectivity">Connectivity</string>
  <string name="Settings.General.Connectivity.HomeServer">Home server</string>
  <string name="Settings.General.Connectivity.HomeServer.Help">Home server information, attach to and detach from home server</string>
  <string name="Settings.General.Connectivity.ServerListener">Server listener</string>
  <string name="Settings.General.Connectivity.ServerListener.Help">Enable notification in detached state, when a MediaPortal 2 server becomes available in the network</string>
  <string name="Settings.General.Connectivity.ClientName">Client name</string>
  <string name="Settings.General.Connectivity.ClientName.Help">Set the name of this MediaPortal 2 client</string>
  <string name="Settings.General.Connectivity.HttpServerPort">HTTP server port</string>
  <string name="Settings.General.Connectivity.HttpServerPort.Help">Set the port of the HTTP Server</string>
  <string name="Settings.General.Connectivity.UseIPv4">Use IPv4</string>
  <string name="Settings.General.Connectivity.UseIPv4.Help">Set if this MediaPortal 2 client should use IPv4 connections to the Home server</string>
  <string name="Settings.General.Connectivity.UseIPv6">Use IPv6</string>
  <string name="Settings.General.Connectivity.UseIPv6.Help">Set if this MediaPortal 2 client should use IPv6 connections to the Home server</string>
  <string name="Settings.General.Connectivity.IPAddressBindings">IP address bindings</string>
  <string name="Settings.General.Connectivity.IPAddressBindings.Help">Set a list of IP addresses which should be used by this MediaPortal 2 client for connections to the Home server</string>

  <string name="Settings.Regional">Regional</string>
  <string name="Settings.Regional.Language">Language</string>
  <string name="Settings.Regional.Language.Main">Language</string>
  <string name="Settings.Regional.Language.Main.Help">Set the main language used in the application</string>

  <string name="Settings.Shares">Media sources</string> <!-- Section name -->
  <string name="Settings.Shares.Configure">Configure media sources</string> <!-- Group name -->
  <string name="Settings.Shares.ConfigureShares.SharesConfiguration">Media sources configuration</string> <!-- Setting -->
  <string name="Settings.Shares.ConfigureShares.SharesConfiguration.Help">Configure all media sources</string>

  <string name="Settings.Shares.Overview">Overview</string> <!-- Group name -->
  <string name="Settings.Shares.Overview.SharesOverview">Media sources overview</string> <!-- Setting -->
  <string name="Settings.Shares.Overview.SharesOverview.Help">Global overview over media sources</string>

  <string name="Settings.Shares.Imports.ReImportAllShares">ReImport all media sources</string>

  <string name="Settings.Plugins">Plugins</string>

  <string name="SharesOverview.OverviewWorkflowNavigationContextDisplayLabel">Media sources overview</string>
  <string name="SharesOverview.Title">Media sources overview</string>
  <string name="SharesOverview.ReImportAllShares">ReImport all media sources</string>
  <string name="SharesOverview.NotConnectedToHomeServer">The home server is not connected, server media source information cannot be retrieved.</string>

  <string name="Shares.NoSharesInThisView">- No media sources in this view -</string>
  <string name="Shares.InvalidPath">INVALID PATH: \'{0}\'</string> <!-- For example: INVALID PATH: 'C:\XXX\YYY' -->
  <string name="Shares.Online">Online</string>
  <string name="Shares.Offline">Offline</string>
  <string name="Shares.ReImport">ReImport</string>
  <string name="Shares.Importing">Importing...</string>

  <!-- Shares configuration workflow -->

  <string name="SharesConfig.SharesOverviewWorkflowNavigationContextDisplayLabel">Media sources configuration</string>
  <string name="SharesConfig.SharesRemoveWorkflowNavigationContextDisplayLabel">Remove media sources</string>
  <string name="SharesConfig.ShareInfoWorkflowNavigationContextDisplayLabel">Media sources info</string>
  <string name="SharesConfig.SharesEditChooseResourceProviderWorkflowNavigationContextDisplayLabel">Choose resource provider</string>
  <string name="SharesConfig.SharesEditEditPathWorkflowNavigationContextDisplayLabel">Edit path</string>
  <string name="SharesConfig.SharesEditChoosePathWorkflowNavigationContextDisplayLabel">Choose path</string>
  <string name="SharesConfig.SharesEditEditNameWorkflowNavigationContextDisplayLabel">Edit name</string>
  <string name="SharesConfig.SharesEditChooseCategoriesWorkflowNavigationContextDisplayLabel">Choose categories</string>
  <string name="SharesConfig.CannotAddSharesTitle">Cannot add media sources</string>
  <string name="SharesConfig.CannotAddShareLocalHomeServerNotConnected">The home server is located at the same computer, thus all media sources must be registered at the server. But the server is not connected at the moment. Please start the home server and try again.</string>
  <string name="SharesConfig.SharesConfiguration.Title">Media sources configuration</string>
  <string name="SharesConfig.NoSharesAvailable">There are no media sources available</string>
  <string name="SharesConfig.ShareInformationHeader">Media sources information</string>
  <string name="SharesConfig.ShareNameInfo">Name:</string>
  <string name="SharesConfig.ShareResourceProviderInfo">Base resource provider:</string>
  <string name="SharesConfig.ShareSystem">System:</string>
  <string name="SharesConfig.SharePathInfo">Path:</string>
  <string name="SharesConfig.ShareResourcePathInfo">Technical path:</string>
  <string name="SharesConfig.ShareMediaCategoriesInfo">Media categories:</string>
  <string name="SharesConfig.ReImportShare">ReImport media source</string>
  <string name="SharesConfig.SetupDefaultShares">Setup default sources</string>
  <string name="SharesConfig.RemoveShares">Remove media sources</string>
  <string name="SharesConfig.EditShare">Edit media source</string>
  <string name="SharesConfig.ChooseSystem">Choose system</string>
  <string name="SharesConfig.ChooseSharesToBeRemoved">Please select the media sources to be removed</string>
  <string name="SharesConfig.ChooseSystemForShare">Choose media source</string>
  <string name="SharesConfig.LocalShare">Client media source</string>
  <string name="SharesConfig.LocalShares">Client media sources</string>
  <string name="SharesConfig.GlobalShare">Server media source</string>
  <string name="SharesConfig.GlobalShares">Server media sources</string>
  <string name="SharesConfig.NoConfigGlobalSharesHomeServerNotConnected">The home server is currently not connected, so server media sources cannot be managed at the moment.</string>
  <string name="SharesConfig.NoConfigLocalSharesHomeServerLocal">The home server is located at the same machine, so only server media sources can be configured.</string>
  <string name="SharesConfig.ChooseResourceProviderForShare">Please select a resource provider for the media source</string>
  <string name="SharesConfig.EditResourceProviderPathForShare">Edit the path to the media source</string>
  <string name="SharesConfig.ResourceProviderPathIsNotValid">Edit a valid path in the choosen resource provider. You can edit a simple path which is understandable by the resource provider. You can also edit a complex path in the format {[Base-ResourceProvider-ID]}://[Base-ResourceProvider-Path]&gt;{[Chained-ResourceProvider-ID]}://[Chained-ResourceProvider-Path]&gt;...</string>
  <string name="SharesConfig.ChooseResourceProviderPathForShare">Choose the path of the media source</string>
  <string name="SharesConfig.EditShareName">Edit the media source\'s display name</string>
  <string name="SharesConfig.ChooseShareCategories">Choose the categories of media contents located in the media source</string>
  <string name="SharesConfig.SharePathExists">A media source with that path already exists</string>
  <string name="SharesConfig.ShareNameExists">A media source with that name already exists</string>
  <string name="SharesConfig.ShareNameEmpty">Edit a name for the media source</string>
  <string name="SharesConfig.EditShareProblemHeader">Problem configuring media source</string>
  <string name="SharesConfig.EditShareProblemText">There was an internal error while configuring the media source</string>
  <string name="SharesConfig.MenuAddShare">Add media source</string>
  <string name="SharesConfig.MenuEditShares">Edit</string>
  <string name="SharesConfig.MenuRemoveShares">Remove media sources</string>
  <string name="SharesConfig.AddServerShare">Add server media source</string> <!-- Must fit for both multiseat and singleseat, that's why we don't write "server share" -->
  <string name="SharesConfig.EditServerShare">Edit server media source</string> <!-- Must fit for both multiseat and singleseat, that's why we don't write "server share" -->
  <string name="SharesConfig.AddLocalShare">Add client media source</string>
  <string name="SharesConfig.EditLocalShare">Edit client media source</string>
  <string name="SharesConfig.UpdateShareRelocateItemsQueryDialogHeader">Update media source</string>
  <string name="SharesConfig.UpdateShareRelocateItemsQueryText.Info">The media source\'s resource provider and/or path have been updated.</string>
  <string name="SharesConfig.UpdateShareRelocateItemsQueryText.Description">The media library\'s information about the media items in that media source can be updated (relocated) or cleared and reimported.</string>
  <string name="SharesConfig.UpdateShareRelocateItemsQueryText.Query">Do you want to relocate or clear and reimport?</string>
  <string name="SharesConfig.Relocate">Relocate</string>
  <string name="SharesConfig.ReImport">ReImport</string>
  <string name="SharesConfig.ManualPathInput">Manual input</string>
  <string name="SharesConfig.UseShareWatcher">Share watcher:</string>
  <string name="SharesConfig.UseShareWatcher.Help">Monitors the source for changes and automatically updates the media library</string>

  <string name="UPnPFrontendServer.DefaultFriendlyName">MediaPortal 2 client</string>
  <string name="UPnPFrontendServer.Manufacturer">Team Mediaportal</string>
  <string name="UPnPFrontendServer.ManufacturerUrl">www.team-mediaportal.com</string>
  <string name="UPnPFrontendServer.ModelDescription">MediaPortal 2 client - the MediaPortal GUI. Plays media content, hosts client media sources and provides the user interface.</string>
  <string name="UPnPFrontendServer.ModelName">MediaPortal 2 client</string>
  <string name="UPnPFrontendServer.ModelNumber">1</string>
<!--  <string name="UPnPFrontendServer.ModelUrl">...</string> -->

  <string name="DaysOfWeek.1">Monday</string>
  <string name="DaysOfWeek.2">Tuesday</string>
  <string name="DaysOfWeek.3">Wednesday</string>
  <string name="DaysOfWeek.4">Thursday</string>
  <string name="DaysOfWeek.5">Friday</string>
  <string name="DaysOfWeek.6">Saturday</string>
  <string name="DaysOfWeek.7">Sunday</string>
  <string name="DaysOfWeek.Monday">Monday</string>
  <string name="DaysOfWeek.Tuesday">Tuesday</string>
  <string name="DaysOfWeek.Wednesday">Wednesday</string>
  <string name="DaysOfWeek.Thursday">Thursday</string>
  <string name="DaysOfWeek.Friday">Friday</string>
  <string name="DaysOfWeek.Saturday">Saturday</string>
  <string name="DaysOfWeek.Sunday">Sunday</string>

  <string name="Months.1">January</string>
  <string name="Months.2">February</string>
  <string name="Months.3">March</string>
  <string name="Months.4">April</string>
  <string name="Months.5">May</string>
  <string name="Months.6">June</string>
  <string name="Months.7">July</string>
  <string name="Months.8">August</string>
  <string name="Months.9">September</string>
  <string name="Months.10">October</string>
  <string name="Months.11">November</string>
  <string name="Months.12">December</string>
  <string name="Months.January">January</string>
  <string name="Months.February">February</string>
  <string name="Months.March">March</string>
  <string name="Months.April">April</string>
  <string name="Months.May">May</string>
  <string name="Months.June">June</string>
  <string name="Months.July">July</string>
  <string name="Months.August">August</string>
  <string name="Months.September">September</string>
  <string name="Months.October">October</string>
  <string name="Months.November">November</string>
  <string name="Months.December">December</string>
</resources>
